thales_remote/__init__.py
thales_remote/connection.py
thales_remote/epc_scpi_handler.py
thales_remote/error.py
thales_remote/file_interface.py
thales_remote/script_wrapper.py
thales_remote-1.2.8.dist-info/licenses/LICENSE
thales_remote-1.2.8.dist-info/METADATA
thales_remote-1.2.8.dist-info/WHEEL
thales_remote-1.2.8.dist-info/top_level.txt
thales_remote-1.2.8.dist-info/RECORD
