Metadata-Version: 2.4
Name: thales_remote
Version: 1.2.8
Summary: Library to control Zahner Zennium potentiostats
Author-email: Maximilian Krapp <maximilian.krapp@zahner.de>
License: MIT License
Project-URL: Documentation, https://doc.zahner.de/thales_remote/
Project-URL: Examples, https://github.com/Zahner-elektrik/Thales-Remote-Python
Project-URL: Source Code, https://github.com/Zahner-elektrik/Thales-Remote-Python
Project-URL: Bug Tracker, https://github.com/Zahner-elektrik/Thales-Remote-Python/issues
Project-URL: Homepage, https://zahner.de/
Keywords: potentiostat,electrochemistry,chemistry,eis,cyclic voltammetry,fuel-cell,battery
Classifier: Development Status :: 5 - Production/Stable
Classifier: Intended Audience :: Developers
Classifier: Intended Audience :: Science/Research
Classifier: Intended Audience :: Education
Classifier: Intended Audience :: Manufacturing
Classifier: Topic :: Scientific/Engineering
Classifier: Topic :: Scientific/Engineering :: Chemistry
Classifier: Topic :: Scientific/Engineering :: Physics
Classifier: Programming Language :: Python :: 3.9
Classifier: Programming Language :: Python :: 3.10
Classifier: Programming Language :: Python :: 3.11
Classifier: Programming Language :: Python :: 3.12
Classifier: License :: OSI Approved :: MIT License
Classifier: Operating System :: OS Independent
Requires-Python: >=3.9
License-File: LICENSE
Requires-Dist: zahner_analysis
Requires-Dist: zahner_potentiostat
Dynamic: license-file
